acachecontrol/__init__.py
acachecontrol/acachecontrol.py
acachecontrol/cache.py
acachecontrol/constants.py
acachecontrol/exceptions.py
acachecontrol/request_context_manager.py
acachecontrol-0.3.7.dist-info/METADATA
acachecontrol-0.3.7.dist-info/WHEEL
acachecontrol-0.3.7.dist-info/top_level.txt
acachecontrol-0.3.7.dist-info/RECORD
