Metadata-Version: 2.4
Name: acachecontrol
Version: 0.3.7
Summary: Cache-Control for aiohttp
Home-page: https://github.com/MasterSergius/acachecontrol
Author: Serhii Buniak, Andrii Ivaniuk
Author-email: master.sergius@gmail.com, andrii.ivaniuk@gmail.com
License: Apache License 2.0
Project-URL: Changelog, https://github.com/MasterSergius/acachecontrol/blob/master/CHANGELOG.md
Project-URL: Issue Tracker, https://github.com/MasterSergius/acachecontrol/issues
Classifier: Development Status :: 5 - Production/Stable
Classifier: Intended Audience :: Developers
Classifier: License :: OSI Approved :: Apache Software License
Classifier: Operating System :: Unix
Classifier: Operating System :: POSIX
Classifier: Programming Language :: Python
Classifier: Programming Language :: Python :: 3
Classifier: Programming Language :: Python :: 3.6
Classifier: Programming Language :: Python :: 3.7
Classifier: Programming Language :: Python :: 3.8
Classifier: Programming Language :: Python :: 3.9
Classifier: Programming Language :: Python :: 3.10
Classifier: Programming Language :: Python :: Implementation :: CPython
Classifier: Programming Language :: Python :: Implementation :: PyPy
Classifier: Topic :: Software Development :: Libraries :: Python Modules
Requires-Python: >=3.6,<4.0
Requires-Dist: aiohttp>=3.10.2
Dynamic: author
Dynamic: author-email
Dynamic: classifier
Dynamic: description
Dynamic: description-content-type
Dynamic: home-page
Dynamic: license
Dynamic: project-url
Dynamic: requires-dist
Dynamic: requires-python
Dynamic: summary
